EzTg/__init__.py
EzTg/inlinekeyboard.py
EzTg/main.py
EzTg-0.2.2.dist-info/METADATA
EzTg-0.2.2.dist-info/WHEEL
EzTg-0.2.2.dist-info/top_level.txt
EzTg-0.2.2.dist-info/RECORD
