Metadata-Version: 2.1
Name: EzTg
Version: 0.2.2
Summary: An api wrapper for telegram easy to use. Coerent according to telegram core.
Home-page: https://github.com/HexyeDEV/EzTg/
Download-URL: https://github.com/HexyeDEV/EzTg/releases
Author: Hexye
Author-email: dragonsale22@gmail.com
Project-URL: Bug Tracker, https://github.com/HexyeDEV/EzTg/issues
Classifier: Programming Language :: Python :: 3.6
Classifier: Programming Language :: Python :: 3.7
Classifier: Programming Language :: Python :: 3.8
Classifier: Programming Language :: Python :: 3.9
Classifier: Programming Language :: Python :: 3.10
Classifier: Programming Language :: Python :: 3.11
Classifier: License :: OSI Approved :: MIT License
Classifier: Operating System :: OS Independent
Requires-Python: >=3.6
Requires-Dist: aiohttp
Requires-Dist: requests
